simpleder/__init__.py
simpleder/der.py
simpleder-0.0.5.dist-info/LICENSE
simpleder-0.0.5.dist-info/METADATA
simpleder-0.0.5.dist-info/WHEEL
simpleder-0.0.5.dist-info/top_level.txt
simpleder-0.0.5.dist-info/RECORD
