Metadata-Version: 2.1
Name: simpleder
Version: 0.0.5
Summary: A lightweight library to compute Diarization Error Rate (DER).
Home-page: https://github.com/wq2012/SimpleDER
Author: Quan Wang
Author-email: quanw@google.com
Classifier: Programming Language :: Python :: 3
Classifier: License :: OSI Approved :: Apache Software License
Classifier: Operating System :: OS Independent
License-File: LICENSE
